dt_pinger.py
dt_pinger-0.1.5.dist-info/entry_points.txt
dt_pinger-0.1.5.dist-info/LICENSE
dt_pinger-0.1.5.dist-info/METADATA
dt_pinger-0.1.5.dist-info/WHEEL
dt_pinger-0.1.5.dist-info/RECORD
